cdktf_local_build/__init__.py
cdktf_local_build/py.typed
cdktf_local_build/_jsii/__init__.py
cdktf_local_build/_jsii/cdktf-local-build@0.0.112.jsii.tgz
cdktf_local_build-0.0.112.dist-info/LICENSE
cdktf_local_build-0.0.112.dist-info/METADATA
cdktf_local_build-0.0.112.dist-info/WHEEL
cdktf_local_build-0.0.112.dist-info/top_level.txt
cdktf_local_build-0.0.112.dist-info/RECORD
