Metadata-Version: 2.1
Name: cdktf-local-build
Version: 0.0.112
Summary: A construct that encapsulates different building methods, e.g. for Node, Rust, Docker.
Home-page: https://github.com/DanielMSchmidt/cdktf-local-build.git
Author: Daniel Schmidt<danielmschmidt92@gmail.com>
License: Apache-2.0
Project-URL: Source, https://github.com/DanielMSchmidt/cdktf-local-build.git
Platform: UNKNOWN
Classifier: Intended Audience :: Developers
Classifier: Operating System :: OS Independent
Classifier: Programming Language :: JavaScript
Classifier: Programming Language :: Python :: 3 :: Only
Classifier: Programming Language :: Python :: 3.7
Classifier: Programming Language :: Python :: 3.8
Classifier: Programming Language :: Python :: 3.9
Classifier: Programming Language :: Python :: 3.10
Classifier: Typing :: Typed
Classifier: Development Status :: 5 - Production/Stable
Classifier: License :: OSI Approved
Requires-Python: ~=3.7
License-File: LICENSE
Requires-Dist: cdktf-cdktf-provider-null (>=0.6.0)
Requires-Dist: cdktf-local-exec (>=0.0.90)
Requires-Dist: cdktf (<0.11.0,>=0.10.1)
Requires-Dist: constructs (<11.0.0,>=10.0.107)
Requires-Dist: jsii (<2.0.0,>=1.58.0)
Requires-Dist: publication (>=0.0.3)
